youngtest/__init__.py
youngtest/youngtest.py
youngtest-1.1.dist-info/LICENSE
youngtest-1.1.dist-info/METADATA
youngtest-1.1.dist-info/WHEEL
youngtest-1.1.dist-info/top_level.txt
youngtest-1.1.dist-info/RECORD
